placebrain_contracts/__init__.py
placebrain_contracts/auth_pb2.py
placebrain_contracts/auth_pb2.pyi
placebrain_contracts-0.1.0.dist-info/METADATA
placebrain_contracts-0.1.0.dist-info/WHEEL
placebrain_contracts-0.1.0.dist-info/RECORD
