Metadata-Version: 2.4
Name: placebrain-contracts
Version: 0.1.0
Summary: Protocol buffer contracts package
Requires-Python: >=3.13
Requires-Dist: protobuf>=6.33.2
